{"animations": [{"loop": false,"offsets": [8,1],"fps": 24,"anim": "idle","indices": [],"name": "BF idle dance"},{"offsets": [8,-5],"indices": [],"fps": 24,"anim": "idle-alt","loop": false,"name": "BF alt idle"},{"offsets": [13,-6],"indices": [],"fps": 24,"anim": "singLEFT","loop": false,"name": "BF NOTE LEFT0"},{"offsets": [-11,-56],"indices": [],"fps": 24,"anim": "singDOWN","loop": false,"name": "BF NOTE DOWN0"},{"offsets": [-36,32],"indices": [],"fps": 24,"anim": "singUP","loop": false,"name": "BF NOTE UP0"},{"offsets": [-48,-6],"indices": [],"fps": 24,"anim": "singRIGHT","loop": false,"name": "BF NOTE RIGHT0"},{"offsets": [13,-9],"indices": [],"fps": 24,"anim": "singLEFTmiss","loop": false,"name": "BF NOTE LEFT MISS"},{"offsets": [-12,-63],"indices": [],"fps": 24,"anim": "singDOWNmiss","loop": false,"name": "BF NOTE DOWN MISS"},{"offsets": [-30,34],"indices": [],"fps": 24,"anim": "singUPmiss","loop": false,"name": "BF NOTE UP MISS"},{"offsets": [-45,-7],"indices": [],"fps": 24,"anim": "singRIGHTmiss","loop": false,"name": "BF NOTE RIGHT MISS"}],"no_antialiasing": false,"image": "characters/alley/bf-mom3-fuck","position": [10,345],"healthicon": "bf-mom3-alt","priorityAnim": [],"flip_x": true,"healthbar_colors": [0,0,0],"camera_position": [80,20],"sing_duration": 4,"scale": 1,"_editor_isPlayer": true}