{"animations": [{"loop": false,"offsets": [-5,0],"anim": "idle","fps": 24,"name": "BF idle dance","indices": []},{"loop": false,"offsets": [4,-7],"anim": "singLEFT","fps": 24,"name": "BF NOTE LEFT0","indices": []},{"loop": false,"offsets": [-20,-51],"anim": "singDOWN","fps": 24,"name": "BF NOTE DOWN0","indices": []},{"loop": false,"offsets": [-46,27],"anim": "singUP","fps": 24,"name": "BF NOTE UP0","indices": []},{"loop": false,"offsets": [-48,-7],"anim": "singRIGHT","fps": 24,"name": "BF NOTE RIGHT0","indices": []},{"loop": false,"offsets": [4,19],"anim": "singLEFTmiss","fps": 24,"name": "BF NOTE LEFT MISS","indices": []},{"loop": false,"offsets": [-20,-21],"anim": "singDOWNmiss","fps": 24,"name": "BF NOTE DOWN MISS","indices": []},{"loop": false,"offsets": [-42,27],"anim": "singUPmiss","fps": 24,"name": "BF NOTE UP MISS","indices": []},{"loop": false,"offsets": [-42,21],"anim": "singRIGHTmiss","fps": 24,"name": "BF NOTE RIGHT MISS","indices": []},{"loop": false,"offsets": [-3,5],"anim": "hey","fps": 24,"name": "BF HEY","indices": []},{"loop": false,"offsets": [15,18],"anim": "hurt","fps": 24,"name": "BF hit","indices": []},{"loop": true,"offsets": [-6,0],"anim": "scared","fps": 24,"name": "BF idle shaking","indices": []},{"loop": false,"offsets": [-7,-15],"anim": "dodge","fps": 24,"name": "boyfriend dodge","indices": []},{"loop": false,"offsets": [-40,-38],"anim": "pre-attack","fps": 24,"name": "bf pre attack","indices": []},{"offsets": [294,271],"loop": false,"fps": 24,"anim": "attack","indices": [],"name": "bf attack"}],"no_antialiasing": false,"image": "characters/BOYFRIEND","position": [0,350],"healthicon": "bf","priorityAnim": ["hey","hurt","scared","dodge","pre-attack","attack"],"flip_x": true,"healthbar_colors": [49,176,209],"camera_position": [0,0],"sing_duration": 4,"scale": 1,"_editor_isPlayer": true}