{"animations": [{"offsets": [-30,-235],"indices": [],"fps": 24,"anim": "idle","loop": false,"name": "GF idle"},{"offsets": [-26,-242],"indices": [],"fps": 24,"anim": "singDOWN","loop": false,"name": "GF Down"},{"offsets": [-28,-230],"indices": [],"fps": 24,"anim": "singUP","loop": false,"name": "GF Up"},{"offsets": [-25,-232],"indices": [],"fps": 24,"anim": "singLEFT","loop": false,"name": "GF Right"},{"offsets": [-33,-236],"indices": [],"fps": 24,"anim": "singRIGHT","loop": false,"name": "gf Left"},{"offsets": [-33,-275],"indices": [],"fps": 24,"anim": "dodge","loop": false,"name": "dodge"}],"no_antialiasing": false,"image": "characters/timelines/duality/dead/gf-tired2","position": [0,100],"healthicon": "gf-deadEnd-4","priorityAnim": ["dodge"],"flip_x": true,"healthbar_colors": [165,0,77],"camera_position": [50,200],"sing_duration": 4,"scale": 1,"_editor_isPlayer": false}