<?xml version="1.0" encoding="utf-8"?>
<TextureAtlas imagePath="bef3.png">
	<!-- Created with Adobe Animate version 24.0.4.28 -->
	<!-- http://www.adobe.com/products/animate.html -->
	<SubTexture name="bef down0000" x="0" y="0" width="665" height="908" frameX="0" frameY="-5" frameWidth="665" frameHeight="913"/>
	<SubTexture name="bef down0001" x="0" y="0" width="665" height="908" frameX="0" frameY="-5" frameWidth="665" frameHeight="913"/>
	<SubTexture name="bef down0002" x="665" y="0" width="654" height="913" frameX="-4" frameY="0" frameWidth="665" frameHeight="913"/>
	<SubTexture name="bef down0003" x="665" y="0" width="654" height="913" frameX="-4" frameY="0" frameWidth="665" frameHeight="913"/>
	<SubTexture name="bef down0004" x="665" y="0" width="654" height="913" frameX="-4" frameY="0" frameWidth="665" frameHeight="913"/>
	<SubTexture name="bef down0005" x="665" y="0" width="654" height="913" frameX="-4" frameY="0" frameWidth="665" frameHeight="913"/>
	<SubTexture name="bef down0006" x="665" y="0" width="654" height="913" frameX="-4" frameY="0" frameWidth="665" frameHeight="913"/>
	<SubTexture name="bef down0007" x="665" y="0" width="654" height="913" frameX="-4" frameY="0" frameWidth="665" frameHeight="913"/>
	<SubTexture name="bef down0008" x="665" y="0" width="654" height="913" frameX="-4" frameY="0" frameWidth="665" frameHeight="913"/>
	<SubTexture name="bef down0009" x="665" y="0" width="654" height="913" frameX="-4" frameY="0" frameWidth="665" frameHeight="913"/>
	<SubTexture name="bef down0010" x="665" y="0" width="654" height="913" frameX="-4" frameY="0" frameWidth="665" frameHeight="913"/>
	<SubTexture name="bef down0011" x="665" y="0" width="654" height="913" frameX="-4" frameY="0" frameWidth="665" frameHeight="913"/>
	<SubTexture name="bef down0012" x="665" y="0" width="654" height="913" frameX="-4" frameY="0" frameWidth="665" frameHeight="913"/>
	<SubTexture name="bef down0013" x="665" y="0" width="654" height="913" frameX="-4" frameY="0" frameWidth="665" frameHeight="913"/>
	<SubTexture name="bef down0014" x="665" y="0" width="654" height="913" frameX="-4" frameY="0" frameWidth="665" frameHeight="913"/>
	<SubTexture name="bef idle0000" x="1319" y="0" width="652" height="917" frameX="-11" frameY="0" frameWidth="676" frameHeight="917"/>
	<SubTexture name="bef idle0001" x="1319" y="0" width="652" height="917" frameX="-11" frameY="0" frameWidth="676" frameHeight="917"/>
	<SubTexture name="bef idle0002" x="1971" y="0" width="653" height="915" frameX="-10" frameY="-2" frameWidth="676" frameHeight="917"/>
	<SubTexture name="bef idle0003" x="1971" y="0" width="653" height="915" frameX="-10" frameY="-2" frameWidth="676" frameHeight="917"/>
	<SubTexture name="bef idle0004" x="2624" y="0" width="659" height="910" frameX="-8" frameY="-7" frameWidth="676" frameHeight="917"/>
	<SubTexture name="bef idle0005" x="2624" y="0" width="659" height="910" frameX="-8" frameY="-7" frameWidth="676" frameHeight="917"/>
	<SubTexture name="bef idle0006" x="3283" y="0" width="676" height="899" frameX="0" frameY="-18" frameWidth="676" frameHeight="917"/>
	<SubTexture name="bef idle0007" x="3283" y="0" width="676" height="899" frameX="0" frameY="-18" frameWidth="676" frameHeight="917"/>
	<SubTexture name="bef idle0008" x="2624" y="0" width="659" height="910" frameX="-8" frameY="-7" frameWidth="676" frameHeight="917"/>
	<SubTexture name="bef idle0009" x="2624" y="0" width="659" height="910" frameX="-8" frameY="-7" frameWidth="676" frameHeight="917"/>
	<SubTexture name="bef idle0010" x="1971" y="0" width="653" height="915" frameX="-10" frameY="-2" frameWidth="676" frameHeight="917"/>
	<SubTexture name="bef idle0011" x="1319" y="0" width="652" height="917" frameX="-11" frameY="0" frameWidth="676" frameHeight="917"/>
	<SubTexture name="bef idle0012" x="1319" y="0" width="652" height="917" frameX="-11" frameY="0" frameWidth="676" frameHeight="917"/>
	<SubTexture name="bef idle0013" x="1319" y="0" width="652" height="917" frameX="-11" frameY="0" frameWidth="676" frameHeight="917"/>
	<SubTexture name="bef idle0014" x="1319" y="0" width="652" height="917" frameX="-11" frameY="0" frameWidth="676" frameHeight="917"/>
	<SubTexture name="bef idle0015" x="1319" y="0" width="652" height="917" frameX="-11" frameY="0" frameWidth="676" frameHeight="917"/>
	<SubTexture name="bef idle0016" x="1319" y="0" width="652" height="917" frameX="-11" frameY="0" frameWidth="676" frameHeight="917"/>
	<SubTexture name="bef left0000" x="0" y="917" width="666" height="918" frameX="0" frameY="0" frameWidth="674" frameHeight="918"/>
	<SubTexture name="bef left0001" x="0" y="917" width="666" height="918" frameX="0" frameY="0" frameWidth="674" frameHeight="918"/>
	<SubTexture name="bef left0002" x="666" y="917" width="662" height="915" frameX="-12" frameY="-3" frameWidth="674" frameHeight="918"/>
	<SubTexture name="bef left0003" x="666" y="917" width="662" height="915" frameX="-12" frameY="-3" frameWidth="674" frameHeight="918"/>
	<SubTexture name="bef left0004" x="666" y="917" width="662" height="915" frameX="-12" frameY="-3" frameWidth="674" frameHeight="918"/>
	<SubTexture name="bef left0005" x="666" y="917" width="662" height="915" frameX="-12" frameY="-3" frameWidth="674" frameHeight="918"/>
	<SubTexture name="bef left0006" x="666" y="917" width="662" height="915" frameX="-12" frameY="-3" frameWidth="674" frameHeight="918"/>
	<SubTexture name="bef left0007" x="666" y="917" width="662" height="915" frameX="-12" frameY="-3" frameWidth="674" frameHeight="918"/>
	<SubTexture name="bef left0008" x="666" y="917" width="662" height="915" frameX="-12" frameY="-3" frameWidth="674" frameHeight="918"/>
	<SubTexture name="bef left0009" x="666" y="917" width="662" height="915" frameX="-12" frameY="-3" frameWidth="674" frameHeight="918"/>
	<SubTexture name="bef left0010" x="666" y="917" width="662" height="915" frameX="-12" frameY="-3" frameWidth="674" frameHeight="918"/>
	<SubTexture name="bef left0011" x="666" y="917" width="662" height="915" frameX="-12" frameY="-3" frameWidth="674" frameHeight="918"/>
	<SubTexture name="bef left0012" x="666" y="917" width="662" height="915" frameX="-12" frameY="-3" frameWidth="674" frameHeight="918"/>
	<SubTexture name="bef left0013" x="666" y="917" width="662" height="915" frameX="-12" frameY="-3" frameWidth="674" frameHeight="918"/>
	<SubTexture name="bef left0014" x="666" y="917" width="662" height="915" frameX="-12" frameY="-3" frameWidth="674" frameHeight="918"/>
	<SubTexture name="bef right0000" x="1328" y="917" width="640" height="908" frameX="-2" frameY="0" frameWidth="642" frameHeight="908"/>
	<SubTexture name="bef right0001" x="1328" y="917" width="640" height="908" frameX="-2" frameY="0" frameWidth="642" frameHeight="908"/>
	<SubTexture name="bef right0002" x="1968" y="917" width="637" height="906" frameX="0" frameY="-2" frameWidth="642" frameHeight="908"/>
	<SubTexture name="bef right0003" x="1968" y="917" width="637" height="906" frameX="0" frameY="-2" frameWidth="642" frameHeight="908"/>
	<SubTexture name="bef right0004" x="1968" y="917" width="637" height="906" frameX="0" frameY="-2" frameWidth="642" frameHeight="908"/>
	<SubTexture name="bef right0005" x="1968" y="917" width="637" height="906" frameX="0" frameY="-2" frameWidth="642" frameHeight="908"/>
	<SubTexture name="bef right0006" x="1968" y="917" width="637" height="906" frameX="0" frameY="-2" frameWidth="642" frameHeight="908"/>
	<SubTexture name="bef right0007" x="1968" y="917" width="637" height="906" frameX="0" frameY="-2" frameWidth="642" frameHeight="908"/>
	<SubTexture name="bef right0008" x="1968" y="917" width="637" height="906" frameX="0" frameY="-2" frameWidth="642" frameHeight="908"/>
	<SubTexture name="bef right0009" x="1968" y="917" width="637" height="906" frameX="0" frameY="-2" frameWidth="642" frameHeight="908"/>
	<SubTexture name="bef right0010" x="1968" y="917" width="637" height="906" frameX="0" frameY="-2" frameWidth="642" frameHeight="908"/>
	<SubTexture name="bef right0011" x="1968" y="917" width="637" height="906" frameX="0" frameY="-2" frameWidth="642" frameHeight="908"/>
	<SubTexture name="bef right0012" x="1968" y="917" width="637" height="906" frameX="0" frameY="-2" frameWidth="642" frameHeight="908"/>
	<SubTexture name="bef right0013" x="1968" y="917" width="637" height="906" frameX="0" frameY="-2" frameWidth="642" frameHeight="908"/>
	<SubTexture name="bef right0014" x="1968" y="917" width="637" height="906" frameX="0" frameY="-2" frameWidth="642" frameHeight="908"/>
	<SubTexture name="bef up0000" x="2605" y="917" width="628" height="927" frameX="-6" frameY="0" frameWidth="634" frameHeight="927"/>
	<SubTexture name="bef up0001" x="2605" y="917" width="628" height="927" frameX="-6" frameY="0" frameWidth="634" frameHeight="927"/>
	<SubTexture name="bef up0002" x="3233" y="917" width="634" height="918" frameX="0" frameY="-9" frameWidth="634" frameHeight="927"/>
	<SubTexture name="bef up0003" x="3233" y="917" width="634" height="918" frameX="0" frameY="-9" frameWidth="634" frameHeight="927"/>
	<SubTexture name="bef up0004" x="3233" y="917" width="634" height="918" frameX="0" frameY="-9" frameWidth="634" frameHeight="927"/>
	<SubTexture name="bef up0005" x="3233" y="917" width="634" height="918" frameX="0" frameY="-9" frameWidth="634" frameHeight="927"/>
	<SubTexture name="bef up0006" x="3233" y="917" width="634" height="918" frameX="0" frameY="-9" frameWidth="634" frameHeight="927"/>
	<SubTexture name="bef up0007" x="3233" y="917" width="634" height="918" frameX="0" frameY="-9" frameWidth="634" frameHeight="927"/>
	<SubTexture name="bef up0008" x="3233" y="917" width="634" height="918" frameX="0" frameY="-9" frameWidth="634" frameHeight="927"/>
	<SubTexture name="bef up0009" x="3233" y="917" width="634" height="918" frameX="0" frameY="-9" frameWidth="634" frameHeight="927"/>
	<SubTexture name="bef up0010" x="3233" y="917" width="634" height="918" frameX="0" frameY="-9" frameWidth="634" frameHeight="927"/>
	<SubTexture name="bef up0011" x="3233" y="917" width="634" height="918" frameX="0" frameY="-9" frameWidth="634" frameHeight="927"/>
	<SubTexture name="bef up0012" x="3233" y="917" width="634" height="918" frameX="0" frameY="-9" frameWidth="634" frameHeight="927"/>
	<SubTexture name="bef up0013" x="3233" y="917" width="634" height="918" frameX="0" frameY="-9" frameWidth="634" frameHeight="927"/>
	<SubTexture name="bef up0014" x="3233" y="917" width="634" height="918" frameX="0" frameY="-9" frameWidth="634" frameHeight="927"/>
</TextureAtlas>
