{"animations": [{"offsets": [-2,-14],"loop": false,"fps": 24,"anim": "idle","indices": [],"name": "Dad idle dance"},{"offsets": [-10,36],"loop": false,"fps": 24,"anim": "singUP","indices": [],"name": "Dad Sing note UP"},{"offsets": [-4,-2],"loop": false,"fps": 24,"anim": "singRIGHT","indices": [],"name": "Dad Sing Note LEFT"},{"offsets": [1,-33],"loop": false,"fps": 24,"anim": "singDOWN","indices": [],"name": "Dad Sing Note DOWN"},{"offsets": [-9,6],"loop": false,"fps": 24,"anim": "singLEFT","indices": [],"name": "dad sing note right"},{"offsets": [-2,-10],"loop": false,"fps": 24,"anim": "transform","indices": [],"name": "Dad eyes on"}],"no_antialiasing": false,"image": "characters/father/definitive/dad-1-alt","position": [0,0],"healthicon": "dad-1-5","priorityAnim": ["transform"],"flip_x": false,"healthbar_colors": [175,102,206],"camera_position": [80,70],"sing_duration": 4,"scale": 1,"_editor_isPlayer": false}